setup.py
vcard/__init__.py
vcard/vcard.py
vcardreader.egg-info/PKG-INFO
vcardreader.egg-info/SOURCES.txt
vcardreader.egg-info/dependency_links.txt
vcardreader.egg-info/entry_points.txt
vcardreader.egg-info/top_level.txt