Metadata-Version: 1.1
Name: vcardreader
Version: 0.3.0
Summary: VCARD parser.
Home-page: http://www.fixedpoint.nl
Author: Jeroen F.J. Laros
Author-email: jlaros@fixedpoint.nl
License: MIT License
Keywords: vcard
Platform: any
Classifier: Development Status :: 3 - Alpha
Classifier: Operating System :: OS Independent
Classifier: Programming Language :: Python
